pmapv/__init__.py
pmapv-0.1.dist-info/METADATA
pmapv-0.1.dist-info/WHEEL
pmapv-0.1.dist-info/top_level.txt
pmapv-0.1.dist-info/RECORD
