Metadata-Version: 2.1
Name: pmapv
Version: 0.1
Summary: parallel mapv
Home-page: http://github.com/nulligor/pmapv
Author: Igor Soares
Author-email: igor.larcs@gmail.com
License: MIT
Platform: UNKNOWN
